{
  "hvalatips-title1": "Enter your card details",
  "hvalatips-title2": "Payment details",
  "hvalatips-iznos": "Amount",
  "hvalatips-title3": "Card number",
  "hvalatips-title4": "Expiry date",
  "hvalatips-title5": "*The service does not have access to your card data, all operations are carried out on the side of the bank",
  "hvalatips-title6": "Return to ",
  "hvalatips-title7": "Merchant Site ",
  "hvalatips-title8": "(without completing payment)",
  "hvalatips-btn1": "Continue",
  "hvalatips-title9": "Note: ",
  "hvalatips-title10": "In the next step, payment verification may be requested through the card issuing bank."
}
 